pybeatsaver/__init__.py
pybeatsaver/beatsaver.py
pybeatsaver/beatsaver_api.py
pybeatsaver/beatsaver_provider.py
pybeatsaver/errors.py
pybeatsaver/http_client.py
pybeatsaver/utils.py
pybeatsaver/version.py
pybeatsaver/models/__init__.py
pybeatsaver/models/auth_request.py
pybeatsaver/models/fields.py
pybeatsaver/models/map_detail.py
pybeatsaver/models/map_detail_metadata.py
pybeatsaver/models/map_difficulty.py
pybeatsaver/models/map_parity_summary.py
pybeatsaver/models/map_stats.py
pybeatsaver/models/map_testplay.py
pybeatsaver/models/map_version.py
pybeatsaver/models/search_response.py
pybeatsaver/models/user_detail.py
pybeatsaver/models/user_diff_stats.py
pybeatsaver/models/user_stats.py
pybeatsaver/models/verify_response.py
pybeatsaver/models/vote_request.py
pybeatsaver/models/vote_response.py
pybeatsaver/models/vote_summary.py
pybeatsaver/models/enum/__init__.py
pybeatsaver/models/enum/account_type.py
pybeatsaver/models/enum/base_enum.py
pybeatsaver/models/enum/characteristic.py
pybeatsaver/models/enum/difficulty.py
pybeatsaver/models/enum/human_enum.py
pybeatsaver/models/enum/leaderboard.py
pybeatsaver/models/enum/map_sort.py
pybeatsaver/models/enum/map_state.py
pybeatsaver/models/enum/map_tag.py
pybeatsaver/models/enum/map_tag_type.py
pybeatsaver/models/enum/search_auto_mapper.py
pybeatsaver/models/enum/search_sort_order.py
pybeatsaver/models/enum/sentiment.py
PyBeatSaver-0.1.16.dist-info/LICENSE
PyBeatSaver-0.1.16.dist-info/METADATA
PyBeatSaver-0.1.16.dist-info/WHEEL
PyBeatSaver-0.1.16.dist-info/top_level.txt
PyBeatSaver-0.1.16.dist-info/RECORD
